sqlalchemy_capture_sql/__init__.py
sqlalchemy_capture_sql/base.py
sqlalchemy_capture_sql-0.2.4.dist-info/LICENSE
sqlalchemy_capture_sql-0.2.4.dist-info/METADATA
sqlalchemy_capture_sql-0.2.4.dist-info/WHEEL
sqlalchemy_capture_sql-0.2.4.dist-info/top_level.txt
sqlalchemy_capture_sql-0.2.4.dist-info/RECORD
