Metadata-Version: 2.1
Name: sqlalchemy-capture-sql
Version: 0.2.4
Summary: A small library that enables capturing SQLAlchemy SQL statements / queries.
Home-page: https://github.com/trebor74hr/sqlalchemy-capture-sql
Author: Robert Lujo
Author-email: trebor74hr@gmail.com
License: UNKNOWN
Platform: UNKNOWN
Classifier: Programming Language :: Python :: 3
Classifier: License :: OSI Approved :: MIT License
Classifier: Operating System :: OS Independent
Requires-Python: >=3.2
License-File: LICENSE
